{
  "slug": "toyota-proace-lease",
  "title": "Toyota Proace",
  "make": "Toyota",
  "model": "Proace",
  "heroImage": "/images/new-vans/Toyota-Proace-Crew-Cab-LeaseScreenshot-2025-04-18-at-16.01-Background-Removed.31-e1744988964795.webp",
  "description": "[![Toyota Proace City…",
  "stockHref": "/vans?make=Toyota&model=Proace",
  "wordCount": 356,
  "body": "![](../images/woocommerce-placeholder-600x600.png.webp)\n\nToyota Proace Lease\n\nase\n\nToyota Proace Lease\n\n## sss\n\n# Toyota Proace Lease\n\n### Petrol, Diesel, Electric\n\n###\n\n### Auto, Manual\n\n[Get Price](#get_price)\n\n-   Keep% of sales proceeds when you decide to sell\n-   No excess mileage charges !\n-   No damage penalty at the end !\n-   PX at any time !\n\n[](tel:0151%20966%208040)\n\n### [Speak To Us Fast](tel:0151%20966%208040)\n\n[Call](tel:0151%20966%208040)\n\n## Enquire\n\n## Related Vans:\n\nView All\n\n## In Stock\n\n## Toyota Proace Crew Cab\n\n## Toyota Proace Crew Cab\n\n### Diesel, Electric\n\n###\n\n### Auto, Manual\n\n### £349.00\n\nFinance lease p/m ex. VAT\n\n### MODEL\n\nTOP VALUE DEAL\n\nGet Price\n\n## In Stock\n\n[![Toyota Proace City Lease](../images/day-exterior-03_EPR2-Background-Removed.png)](https://www.vansales.com/product/toyota-proace-city-lease/)\n\n## Toyota Proace City Lease\n\n## Toyota Proace City Lease\n\n### Diesel, Electric\n\n###\n\n### Auto, Manual\n\n### £275.00\n\nFinance lease p/m ex. VAT\n\n### MODEL\n\nTOP VALUE DEAL\n\nGet Price\n\n## In Stock\n\n[![Toyota Hilux Lease](../images/exterior-4-e1745077190335.webp)](https://www.vansales.com/product/toyota-hilux-lease/)\n\n## Toyota Hilux Lease\n\n## \n\nFinance Lease deposits from £500 Monthly payments worked at £5000\n\nNo excess mileage charges\n\nNo damage fines\n\nKeep% of sales proceeds\n\nwhen you sell\n\n### Diesel, Electric\n\n###\n\n### Auto\n\n### £479.00\n\nFinance lease p/m ex. VAT\n\n### MODEL\n\nTOP VALUE DEAL\n\nGet Price\n\n## In Stock\n\n[![Toyota Proace Lease](../images/day-exterior-6_EPR_43FT-Background-Removed.png)](https://www.vansales.com/product/toyota-proace-lease-2/)\n\n## Toyota Proace Lease\n\n## Finance Lease No excess mileage charges No damage fines Keep% of sales proceeds\n\n### Diesel, Electric\n\n###\n\n### Auto, Manual\n\n### £299.00\n\nFinance lease p/m ex. VAT\n\n### MODEL\n\nTOP VALUE DEAL\n\nGet Price\n\nView All"
}